chemrel/__init__.py
chemrel/cli.py
chemrel/cli_constants.py
chemrel/functions/__init__.py
chemrel/functions/auxiliary.py
chemrel/functions/model.py
chemrel/functions/parser.py
chemrel/functions/pipeline.py
chemrel/functions/predict.py
chemrel/functions/relutils.py
chemrel/functions/test.py
chemrel-1.0.2.dist-info/METADATA
chemrel-1.0.2.dist-info/WHEEL
chemrel-1.0.2.dist-info/entry_points.txt
chemrel-1.0.2.dist-info/licenses/LICENSE
chemrel-1.0.2.dist-info/RECORD
