Metadata-Version: 2.1
Name: chemrel
Version: 1.0.2
Summary: A project which focuses on automating and transferring chemical data extraction using span categorization and relation extraction models.
License-File: LICENSE
Requires-Python: >=3.8
Requires-Dist: httpx
Requires-Dist: huggingface-hub
Requires-Dist: jsonlines
Requires-Dist: nltk
Requires-Dist: pymupdf
Requires-Dist: regex
Requires-Dist: rich
Requires-Dist: spacy
Requires-Dist: spacy-transformers
Requires-Dist: typer
Requires-Dist: urllib3<2.0
